{
  "products": [
    {
      "id": 1,
      "name": "Bravo Sunglasses",
      "price": 150,
      "discountPrice": 100,
      "image": "https://i.ibb.co/TW7FBjW/block1mg.png"
    },
    {
      "id": 2,
      "name": "Vincent Chase",
      "price": 150,
      "discountPrice": 120,
      "image": "https://i.ibb.co/NV6YLkc/block2img.png"
    },
    {
      "id": 3,
      "name": "John Jacobs",
      "price": null,
      "discountPrice": 100,
      "image": "https://i.ibb.co/NV6YLkc/block2img.png"
    },
    {
      "id": 4,
      "name": "Tommy Hilfiger",
      "price": 150,
      "discountPrice": 130,
      "image": "https://i.ibb.co/34snCPc/block4img.png"
    },
    {
      "id": 5,
      "name": "Ray Ban",
      "price": null,
      "discountPrice": 100,
      "image": "https://i.ibb.co/qMqp6jx/block5img.png"
    },
    {
      "id": 6,
      "name": "Occhiali",
      "price": 150,
      "discountPrice": 110,
      "image": "https://i.ibb.co/TW7FBjW/block1mg.png"
    }
  ]
}
